Workbook

Sheet 01_Control_Panel
A1: Setting | B1: Value | C1: Notes
A2: Base Currency | B2: FJD | C2: Your local currency
A3: VAT Rate | B3: 0.125 | C3: Standard VAT
A4: Quote Validity | B4: 14 | C4: Days

Sheet 02_Supplier_Input
A4: Line | B4: Supplier | C4: Description | D4: Category | E4: Qty | F4: Unit Cost (Supp) | G4: Currency | H4: FX Rate | I4: Unit Cost (FJD) | J4: Ship Method | K4: Ship Value | L4: Ship Cost (FJD) | M4: Duty % | N4: Duty (FJD) | O4: Landed Cost | P4: Target GM% | Q4: Override GM% | R4: VAT Excl. (FJD) | S4: VAT Incl. (FJD) | T4: Total Line (FJD)
A5: 1 | B5: Westcon NZ | C5: 93001 Switch | D5: Networking | E5: 1 | F5: 300 | G5: =IFERROR(VLOOKUP(B5, '07_Supplier_List'!A:B, 2, FALSE), "USD") -> NZD | H5: =VLOOKUP(G5, '03_FX_Rates'!A:B, 2, FALSE) -> 1.4 | I5: =F5*H5 -> 420 | J5: Percent | K5: 0.05 | L5: =IF(J5="Percent", I5*K5, K5) -> 21 | M5: =IFERROR(VLOOKUP(D5, '04_Logistics_Taxes'!A:B, 2, FALSE), 0) -> 0.05 | N5: =(I5+L5)*M5 -> 22.05 | O5: =I5+L5+N5 -> 463.05 | P5: =IF(Q5<>"", Q5, IFERROR(VLOOKUP(D5, '05_Margin_Engine'!A:B, 2, FALSE), 0)) -> 0.25 | R5: =IF(Q5<>"", O5/(1-Q5), O5/(1-P5)) -> 617.4 | S5: =(R5*'01_Control_Panel'!$B$3)+R5 -> 694.575 | T5: =S5*E5 -> 694.575
A6: 2 | B6: Ingram Micro | C6: AP | D6: Networking | E6: 1 | F6: 200 | G6: =IFERROR(VLOOKUP(B6, '07_Supplier_List'!A:B, 2, FALSE), "USD") -> AUD | H6: =VLOOKUP(G6, '03_FX_Rates'!A:B, 2, FALSE) -> 1.5 | I6: =F6*H6 -> 300 | J6: Percent | K6: 0.05 | L6: =IF(J6="Percent", I6*K6, K6) -> 15 | M6: =IFERROR(VLOOKUP(D6, '04_Logistics_Taxes'!A:B, 2, FALSE), 0) -> 0.05 | N6: =(I6+L6)*M6 -> 15.75 | O6: =I6+L6+N6 -> 330.75 | P6: =IF(Q6<>"", Q6, IFERROR(VLOOKUP(D6, '05_Margin_Engine'!A:B, 2, FALSE), 0)) -> 0.25 | R6: =IF(Q6<>"", O6/(1-Q6), O6/(1-P6)) -> 441 | S6: =(R6*'01_Control_Panel'!$B$3)+R6 -> 496.125 | T6: =S6*E6 -> 496.125
A7: 3 | B7: Comvergence Pty Ltd | E7: 1 | G7: =IFERROR(VLOOKUP(B7, '07_Supplier_List'!A:B, 2, FALSE), "USD") -> AUD | H7: =VLOOKUP(G7, '03_FX_Rates'!A:B, 2, FALSE) -> 1.5 | I7: =F7*H7 -> 0 | J7: Percent | K7: 0.05 | L7: =IF(J7="Percent", I7*K7, K7) -> 0 | M7: =IFERROR(VLOOKUP(D7, '04_Logistics_Taxes'!A:B, 2, FALSE), 0) -> 0 | N7: =(I7+L7)*M7 -> 0 | O7: =I7+L7+N7 -> 0 | P7: =IF(Q7<>"", Q7, IFERROR(VLOOKUP(D7, '05_Margin_Engine'!A:B, 2, FALSE), 0)) -> 0 | R7: =IF(Q7<>"", O7/(1-Q7), O7/(1-P7)) -> 0 | S7: =(R7*'01_Control_Panel'!$B$3)+R7 -> 0 | T7: =S7*E7 -> 0
A8: 4 | E8: 1 | G8: =IFERROR(VLOOKUP(B8, '07_Supplier_List'!A:B, 2, FALSE), "USD") -> USD | H8: =VLOOKUP(G8, '03_FX_Rates'!A:B, 2, FALSE) -> 2.25 | I8: =F8*H8 -> 0 | J8: Percent | K8: 0.05 | L8: =IF(J8="Percent", I8*K8, K8) -> 0 | M8: =IFERROR(VLOOKUP(D8, '04_Logistics_Taxes'!A:B, 2, FALSE), 0) -> 0 | N8: =(I8+L8)*M8 -> 0 | O8: =I8+L8+N8 -> 0 | P8: =IF(Q8<>"", Q8, IFERROR(VLOOKUP(D8, '05_Margin_Engine'!A:B, 2, FALSE), 0)) -> 0 | R8: =IF(Q8<>"", O8/(1-Q8), O8/(1-P8)) -> 0 | S8: =(R8*'01_Control_Panel'!$B$3)+R8 -> 0 | T8: =S8*E8 -> 0
A9: 5 | E9: 1 | G9: =IFERROR(VLOOKUP(B9, '07_Supplier_List'!A:B, 2, FALSE), "USD") -> USD | H9: =VLOOKUP(G9, '03_FX_Rates'!A:B, 2, FALSE) -> 2.25 | I9: =F9*H9 -> 0 | J9: Percent | K9: 0.05 | L9: =IF(J9="Percent", I9*K9, K9) -> 0 | M9: =IFERROR(VLOOKUP(D9, '04_Logistics_Taxes'!A:B, 2, FALSE), 0) -> 0 | N9: =(I9+L9)*M9 -> 0 | O9: =I9+L9+N9 -> 0 | P9: =IF(Q9<>"", Q9, IFERROR(VLOOKUP(D9, '05_Margin_Engine'!A:B, 2, FALSE), 0)) -> 0 | R9: =IF(Q9<>"", O9/(1-Q9), O9/(1-P9)) -> 0 | S9: =(R9*'01_Control_Panel'!$B$3)+R9 -> 0 | T9: =S9*E9 -> 0
A10: 6 | E10: 1 | G10: =IFERROR(VLOOKUP(B10, '07_Supplier_List'!A:B, 2, FALSE), "USD") -> USD | H10: =VLOOKUP(G10, '03_FX_Rates'!A:B, 2, FALSE) -> 2.25 | I10: =F10*H10 -> 0 | J10: Percent | K10: 0.05 | L10: =IF(J10="Percent", I10*K10, K10) -> 0 | M10: =IFERROR(VLOOKUP(D11, '04_Logistics_Taxes'!A:B, 2, FALSE), 0) -> 0 | N10: =(I10+L10)*M10 -> 0 | O10: =I10+L10+N10 -> 0 | P10: =IF(Q10<>"", Q10, IFERROR(VLOOKUP(D10, '05_Margin_Engine'!A:B, 2, FALSE), 0)) -> 0 | R10: =IF(Q10<>"", O10/(1-Q10), O10/(1-P10)) -> 0 | S10: =(R10*'01_Control_Panel'!$B$3)+R10 -> 0 | T10: =S10*E10 -> 0
A11: 7 | E11: 1 | G11: =IFERROR(VLOOKUP(B11, '07_Supplier_List'!A:B, 2, FALSE), "USD") -> USD | H11: =VLOOKUP(G11, '03_FX_Rates'!A:B, 2, FALSE) -> 2.25 | I11: =F11*H11 -> 0 | J11: Percent | K11: 0.05 | L11: =IF(J11="Percent", I11*K11, K11) -> 0 | M11: =IFERROR(VLOOKUP(#REF!, '04_Logistics_Taxes'!A:B, 2, FALSE), 0) -> 0 | N11: =(I11+L11)*M11 -> 0 | O11: =I11+L11+N11 -> 0 | P11: =IF(Q11<>"", Q11, IFERROR(VLOOKUP(D11, '05_Margin_Engine'!A:B, 2, FALSE), 0)) -> 0 | R11: =IF(Q11<>"", O11/(1-Q11), O11/(1-P11)) -> 0 | S11: =(R11*'01_Control_Panel'!$B$3)+R11 -> 0 | T11: =S11*E11 -> 0
A12: 8 | E12: 1 | G12: =IFERROR(VLOOKUP(B12, '07_Supplier_List'!A:B, 2, FALSE), "USD") -> USD | H12: =VLOOKUP(G12, '03_FX_Rates'!A:B, 2, FALSE) -> 2.25 | I12: =F12*H12 -> 0 | J12: Percent | K12: 0.05 | L12: =IF(J12="Percent", I12*K12, K12) -> 0 | M12: =IFERROR(VLOOKUP(D12, '04_Logistics_Taxes'!A:B, 2, FALSE), 0) -> 0 | N12: =(I12+L12)*M12 -> 0 | O12: =I12+L12+N12 -> 0 | P12: =IF(Q12<>"", Q12, IFERROR(VLOOKUP(D12, '05_Margin_Engine'!A:B, 2, FALSE), 0)) -> 0 | R12: =IF(Q12<>"", O12/(1-Q12), O12/(1-P12)) -> 0 | S12: =(R12*'01_Control_Panel'!$B$3)+R12 -> 0 | T12: =S12*E12 -> 0
A13: 9 | E13: 1 | G13: =IFERROR(VLOOKUP(B13, '07_Supplier_List'!A:B, 2, FALSE), "USD") -> USD | H13: =VLOOKUP(G13, '03_FX_Rates'!A:B, 2, FALSE) -> 2.25 | I13: =F13*H13 -> 0 | J13: Percent | K13: 0.05 | L13: =IF(J13="Percent", I13*K13, K13) -> 0 | M13: =IFERROR(VLOOKUP(D13, '04_Logistics_Taxes'!A:B, 2, FALSE), 0) -> 0 | N13: =(I13+L13)*M13 -> 0 | O13: =I13+L13+N13 -> 0 | P13: =IF(Q13<>"", Q13, IFERROR(VLOOKUP(D13, '05_Margin_Engine'!A:B, 2, FALSE), 0)) -> 0 | R13: =IF(Q13<>"", O13/(1-Q13), O13/(1-P13)) -> 0 | S13: =(R13*'01_Control_Panel'!$B$3)+R13 -> 0 | T13: =S13*E13 -> 0
A14: 10 | E14: 1 | G14: =IFERROR(VLOOKUP(B14, '07_Supplier_List'!A:B, 2, FALSE), "USD") -> USD | H14: =VLOOKUP(G14, '03_FX_Rates'!A:B, 2, FALSE) -> 2.25 | I14: =F14*H14 -> 0 | J14: Percent | K14: 0.05 | L14: =IF(J14="Percent", I14*K14, K14) -> 0 | M14: =IFERROR(VLOOKUP(D14, '04_Logistics_Taxes'!A:B, 2, FALSE), 0) -> 0 | N14: =(I14+L14)*M14 -> 0 | O14: =I14+L14+N14 -> 0 | P14: =IF(Q14<>"", Q14, IFERROR(VLOOKUP(D14, '05_Margin_Engine'!A:B, 2, FALSE), 0)) -> 0 | R14: =IF(Q14<>"", O14/(1-Q14), O14/(1-P14)) -> 0 | S14: =(R14*'01_Control_Panel'!$B$3)+R14 -> 0 | T14: =S14*E14 -> 0
A15: 11 | E15: 1 | G15: =IFERROR(VLOOKUP(B15, '07_Supplier_List'!A:B, 2, FALSE), "USD") -> USD | H15: =VLOOKUP(G15, '03_FX_Rates'!A:B, 2, FALSE) -> 2.25 | I15: =F15*H15 -> 0 | J15: Percent | K15: 0.05 | L15: =IF(J15="Percent", I15*K15, K15) -> 0 | M15: =IFERROR(VLOOKUP(D15, '04_Logistics_Taxes'!A:B, 2, FALSE), 0) -> 0 | N15: =(I15+L15)*M15 -> 0 | O15: =I15+L15+N15 -> 0 | P15: =IF(Q15<>"", Q15, IFERROR(VLOOKUP(D15, '05_Margin_Engine'!A:B, 2, FALSE), 0)) -> 0 | R15: =IF(Q15<>"", O15/(1-Q15), O15/(1-P15)) -> 0 | S15: =(R15*'01_Control_Panel'!$B$3)+R15 -> 0 | T15: =S15*E15 -> 0
A16: 12 | E16: 1 | G16: =IFERROR(VLOOKUP(B16, '07_Supplier_List'!A:B, 2, FALSE), "USD") -> USD | H16: =VLOOKUP(G16, '03_FX_Rates'!A:B, 2, FALSE) -> 2.25 | I16: =F16*H16 -> 0 | J16: Percent | K16: 0.05 | L16: =IF(J16="Percent", I16*K16, K16) -> 0 | M16: =IFERROR(VLOOKUP(D16, '04_Logistics_Taxes'!A:B, 2, FALSE), 0) -> 0 | N16: =(I16+L16)*M16 -> 0 | O16: =I16+L16+N16 -> 0 | P16: =IF(Q16<>"", Q16, IFERROR(VLOOKUP(D16, '05_Margin_Engine'!A:B, 2, FALSE), 0)) -> 0 | R16: =IF(Q16<>"", O16/(1-Q16), O16/(1-P16)) -> 0 | S16: =(R16*'01_Control_Panel'!$B$3)+R16 -> 0 | T16: =S16*E16 -> 0
A17: 13 | E17: 1 | G17: =IFERROR(VLOOKUP(B17, '07_Supplier_List'!A:B, 2, FALSE), "USD") -> USD | H17: =VLOOKUP(G17, '03_FX_Rates'!A:B, 2, FALSE) -> 2.25 | I17: =F17*H17 -> 0 | J17: Percent | K17: 0.05 | L17: =IF(J17="Percent", I17*K17, K17) -> 0 | M17: =IFERROR(VLOOKUP(D17, '04_Logistics_Taxes'!A:B, 2, FALSE), 0) -> 0 | N17: =(I17+L17)*M17 -> 0 | O17: =I17+L17+N17 -> 0 | P17: =IF(Q17<>"", Q17, IFERROR(VLOOKUP(D17, '05_Margin_Engine'!A:B, 2, FALSE), 0)) -> 0 | R17: =IF(Q17<>"", O17/(1-Q17), O17/(1-P17)) -> 0 | S17: =(R17*'01_Control_Panel'!$B$3)+R17 -> 0 | T17: =S17*E17 -> 0
A18: 14 | E18: 1 | G18: =IFERROR(VLOOKUP(B18, '07_Supplier_List'!A:B, 2, FALSE), "USD") -> USD | H18: =VLOOKUP(G18, '03_FX_Rates'!A:B, 2, FALSE) -> 2.25 | I18: =F18*H18 -> 0 | J18: Percent | K18: 0.05 | L18: =IF(J18="Percent", I18*K18, K18) -> 0 | M18: =IFERROR(VLOOKUP(D18, '04_Logistics_Taxes'!A:B, 2, FALSE), 0) -> 0 | N18: =(I18+L18)*M18 -> 0 | O18: =I18+L18+N18 -> 0 | P18: =IF(Q18<>"", Q18, IFERROR(VLOOKUP(D18, '05_Margin_Engine'!A:B, 2, FALSE), 0)) -> 0 | R18: =IF(Q18<>"", O18/(1-Q18), O18/(1-P18)) -> 0 | S18: =(R18*'01_Control_Panel'!$B$3)+R18 -> 0 | T18: =S18*E18 -> 0
A19: 15 | E19: 1 | G19: =IFERROR(VLOOKUP(B19, '07_Supplier_List'!A:B, 2, FALSE), "USD") -> USD | H19: =VLOOKUP(G19, '03_FX_Rates'!A:B, 2, FALSE) -> 2.25 | I19: =F19*H19 -> 0 | J19: Percent | K19: 0.05 | L19: =IF(J19="Percent", I19*K19, K19) -> 0 | M19: =IFERROR(VLOOKUP(D19, '04_Logistics_Taxes'!A:B, 2, FALSE), 0) -> 0 | N19: =(I19+L19)*M19 -> 0 | O19: =I19+L19+N19 -> 0 | P19: =IF(Q19<>"", Q19, IFERROR(VLOOKUP(D19, '05_Margin_Engine'!A:B, 2, FALSE), 0)) -> 0 | R19: =IF(Q19<>"", O19/(1-Q19), O19/(1-P19)) -> 0 | S19: =(R19*'01_Control_Panel'!$B$3)+R19 -> 0 | T19: =S19*E19 -> 0
A20: 16 | E20: 1 | G20: =IFERROR(VLOOKUP(B20, '07_Supplier_List'!A:B, 2, FALSE), "USD") -> USD | H20: =VLOOKUP(G20, '03_FX_Rates'!A:B, 2, FALSE) -> 2.25 | I20: =F20*H20 -> 0 | J20: Percent | K20: 0.05 | L20: =IF(J20="Percent", I20*K20, K20) -> 0 | M20: =IFERROR(VLOOKUP(D20, '04_Logistics_Taxes'!A:B, 2, FALSE), 0) -> 0 | N20: =(I20+L20)*M20 -> 0 | O20: =I20+L20+N20 -> 0 | P20: =IF(Q20<>"", Q20, IFERROR(VLOOKUP(D20, '05_Margin_Engine'!A:B, 2, FALSE), 0)) -> 0 | R20: =IF(Q20<>"", O20/(1-Q20), O20/(1-P20)) -> 0 | S20: =(R20*'01_Control_Panel'!$B$3)+R20 -> 0 | T20: =S20*E20 -> 0
A21: 17 | E21: 1 | G21: =IFERROR(VLOOKUP(B21, '07_Supplier_List'!A:B, 2, FALSE), "USD") -> USD | H21: =VLOOKUP(G21, '03_FX_Rates'!A:B, 2, FALSE) -> 2.25 | I21: =F21*H21 -> 0 | J21: Percent | K21: 0.05 | L21: =IF(J21="Percent", I21*K21, K21) -> 0 | M21: =IFERROR(VLOOKUP(D21, '04_Logistics_Taxes'!A:B, 2, FALSE), 0) -> 0 | N21: =(I21+L21)*M21 -> 0 | O21: =I21+L21+N21 -> 0 | P21: =IF(Q21<>"", Q21, IFERROR(VLOOKUP(D21, '05_Margin_Engine'!A:B, 2, FALSE), 0)) -> 0 | R21: =IF(Q21<>"", O21/(1-Q21), O21/(1-P21)) -> 0 | S21: =(R21*'01_Control_Panel'!$B$3)+R21 -> 0 | T21: =S21*E21 -> 0
A22: 18 | E22: 1 | G22: =IFERROR(VLOOKUP(B22, '07_Supplier_List'!A:B, 2, FALSE), "USD") -> USD | H22: =VLOOKUP(G22, '03_FX_Rates'!A:B, 2, FALSE) -> 2.25 | I22: =F22*H22 -> 0 | J22: Percent | K22: 0.05 | L22: =IF(J22="Percent", I22*K22, K22) -> 0 | M22: =IFERROR(VLOOKUP(D22, '04_Logistics_Taxes'!A:B, 2, FALSE), 0) -> 0 | N22: =(I22+L22)*M22 -> 0 | O22: =I22+L22+N22 -> 0 | P22: =IF(Q22<>"", Q22, IFERROR(VLOOKUP(D22, '05_Margin_Engine'!A:B, 2, FALSE), 0)) -> 0 | R22: =IF(Q22<>"", O22/(1-Q22), O22/(1-P22)) -> 0 | S22: =(R22*'01_Control_Panel'!$B$3)+R22 -> 0 | T22: =S22*E22 -> 0
A23: 19 | E23: 1 | G23: =IFERROR(VLOOKUP(B23, '07_Supplier_List'!A:B, 2, FALSE), "USD") -> USD | H23: =VLOOKUP(G23, '03_FX_Rates'!A:B, 2, FALSE) -> 2.25 | I23: =F23*H23 -> 0 | J23: Percent | K23: 0.05 | L23: =IF(J23="Percent", I23*K23, K23) -> 0 | M23: =IFERROR(VLOOKUP(D23, '04_Logistics_Taxes'!A:B, 2, FALSE), 0) -> 0 | N23: =(I23+L23)*M23 -> 0 | O23: =I23+L23+N23 -> 0 | P23: =IF(Q23<>"", Q23, IFERROR(VLOOKUP(D23, '05_Margin_Engine'!A:B, 2, FALSE), 0)) -> 0 | R23: =IF(Q23<>"", O23/(1-Q23), O23/(1-P23)) -> 0 | S23: =(R23*'01_Control_Panel'!$B$3)+R23 -> 0 | T23: =S23*E23 -> 0
... A53: 49 | E53: 1 | G53: =IFERROR(VLOOKUP(B53, '07_Supplier_List'!A:B, 2, FALSE), "USD") -> USD | H53: =VLOOKUP(G53, '03_FX_Rates'!A:B, 2, FALSE) -> 2.25 | I53: =F53*H53 -> 0 | J53: Percent | K53: 0.05 | L53: =IF(J53="Percent", I53*K53, K53) -> 0 | M53: =IFERROR(VLOOKUP(D53, '04_Logistics_Taxes'!A:B, 2, FALSE), 0) -> 0 | N53: =(I53+L53)*M53 -> 0 | O53: =I53+L53+N53 -> 0 | P53: =IF(Q53<>"", Q53, IFERROR(VLOOKUP(D53, '05_Margin_Engine'!A:B, 2, FALSE), 0)) -> 0 | R53: =IF(Q53<>"", O53/(1-Q53), O53/(1-P53)) -> 0 | S53: =(R53*'01_Control_Panel'!$B$3)+R53 -> 0 | T53: =S53*E53 -> 0
M54: =IFERROR(VLOOKUP(D54, '04_Logistics_Taxes'!A:B, 2, FALSE), 0) -> 0

Sheet 03_FX_Rates
A1: Currency | B1: Rate to FJD | C1: Last Update
A2: USD | B2: 2.25 | C2: 46037.374
A3: AUD | B3: 1.5 | C3: 46037.374
A4: NZD | B4: 1.4 | C4: 46037.374
A5: EUR | B5: 2.5 | C5: 46037.374
A6: FJD | B6: 1 | C6: 46037

Sheet 04_Logistics_Taxes
A1: Category | B1: Duty Rate | C1: Notes
A2: Networking | B2: 0.05 | C2: Switches/Routers
A3: Security | B3: 0.05 | C3: Firewalls
A4: Server | B4: 0.05 | C4: Hardware
A5: Cloud | B5: 0 | C5: Virtual Goods
A6: Services | B6: 0 | C6: Labor
A7: Cabling | B7: 0.15 | C7: Physical Infra

Sheet 05_Margin_Engine
A1: Category | B1: Target GM | C1: Notes
A2: Networking | B2: 0.25 | C2: Standard
A3: Security | B3: 0.3 | C3: High Value
A4: Server | B4: 0.3 | C4: Competitive
A5: Cloud | B5: 0.15 | C5: Recurring
A6: Services | B6: 0.4 | C6: Pure Margin
A7: Cabling | B7: 0.35 | C7: Accessory

Sheet 06_Quote_Output
B1: CUSTOMER QUOTE
B4: Quote Number | C4: 0
B5: Client | C5: 0
B6: Quote Date | C6: 46023
B7: Valid Until | C7: =C6 + '01_Control_Panel'!$B$4 -> 46037
B8: Currency | C8: FJD
A11: # | B11: Description | C11: Qty | D11: Unit Price | E11: Total (ex VAT) | F11: Total (in VAT) | G11: Notes
A12: 1 | B12: ='02_Supplier_Input'!C5 -> 93001 Switch | C12: ='02_Supplier_Input'!E5 -> 1 | D12: ='02_Supplier_Input'!R5 -> 617.4 | E12: =D12*C12 -> 617.4 | F12: ='02_Supplier_Input'!T5 -> 694.575
A13: 2 | B13: ='02_Supplier_Input'!C6 -> AP | C13: ='02_Supplier_Input'!E6 -> 1 | D13: ='02_Supplier_Input'!R6 -> 441 | E13: =D13*C13 -> 441 | F13: ='02_Supplier_Input'!T6 -> 496.125
A14: 3 | B14: ='02_Supplier_Input'!C7 -> 0 | C14: ='02_Supplier_Input'!E7 -> 1 | D14: ='02_Supplier_Input'!R7 -> 0 | E14: =D14*C14 -> 0 | F14: ='02_Supplier_Input'!T7 -> 0
A15: 4 | B15: ='02_Supplier_Input'!C8 -> 0 | C15: ='02_Supplier_Input'!E8 -> 1 | D15: ='02_Supplier_Input'!R8 -> 0 | E15: =D15*C15 -> 0 | F15: ='02_Supplier_Input'!T8 -> 0
A16: 5 | B16: ='02_Supplier_Input'!C9 -> 0 | C16: ='02_Supplier_Input'!E9 -> 1 | D16: ='02_Supplier_Input'!R9 -> 0 | E16: =D16*C16 -> 0 | F16: ='02_Supplier_Input'!T9 -> 0
A17: 6 | B17: ='02_Supplier_Input'!C10 -> 0 | C17: ='02_Supplier_Input'!E10 -> 1 | D17: ='02_Supplier_Input'!R10 -> 0 | E17: =D17*C17 -> 0 | F17: ='02_Supplier_Input'!T10 -> 0
A18: 7 | B18: ='02_Supplier_Input'!C11 -> 0 | C18: ='02_Supplier_Input'!E11 -> 1 | D18: ='02_Supplier_Input'!R11 -> 0 | E18: =D18*C18 -> 0 | F18: ='02_Supplier_Input'!T11 -> 0
A19: 8 | B19: ='02_Supplier_Input'!C12 -> 0 | C19: ='02_Supplier_Input'!E12 -> 1 | D19: ='02_Supplier_Input'!R12 -> 0 | E19: =D19*C19 -> 0 | F19: ='02_Supplier_Input'!T12 -> 0
A20: 9 | B20: ='02_Supplier_Input'!C13 -> 0 | C20: ='02_Supplier_Input'!E13 -> 1 | D20: ='02_Supplier_Input'!R13 -> 0 | E20: =D20*C20 -> 0 | F20: ='02_Supplier_Input'!T13 -> 0
A21: 10 | B21: ='02_Supplier_Input'!C14 -> 0 | C21: ='02_Supplier_Input'!E14 -> 1 | D21: ='02_Supplier_Input'!R14 -> 0 | E21: =D21*C21 -> 0 | F21: ='02_Supplier_Input'!T14 -> 0
A22: 11 | B22: ='02_Supplier_Input'!C15 -> 0 | C22: ='02_Supplier_Input'!E15 -> 1 | D22: ='02_Supplier_Input'!R15 -> 0 | E22: =D22*C22 -> 0 | F22: ='02_Supplier_Input'!T15 -> 0
A23: 12 | B23: ='02_Supplier_Input'!C16 -> 0 | C23: ='02_Supplier_Input'!E16 -> 1 | D23: ='02_Supplier_Input'!R16 -> 0 | E23: =D23*C23 -> 0 | F23: ='02_Supplier_Input'!T16 -> 0
... A60: 49 | B60: ='02_Supplier_Input'!C53 -> 0 | C60: ='02_Supplier_Input'!E53 -> 1 | D60: ='02_Supplier_Input'!R53 -> 0 | E60: =D60*C60 -> 0 | F60: ='02_Supplier_Input'!T53 -> 0
E64: Subtotal (ex VAT) | F64: =SUM(E12:E60) -> 1058.4
E65: Subtotal (in VAT) | F65: =SUM(F12:F60) -> 1190.7
E66: Grand Total | F66: =F65 -> 1190.7
B67: Notes / Disclaimers:
B68: • Prices are in FJD and valid for the quote validity period unless otherwise stated.
B69: • FX and supplier pricing may change; if FX rates are older than the validity window, approval is required.
B70: • Lead times subject to supplier stock and shipping schedules.
B71: • Installation/support scope to be confirmed during project kickoff where applicable.

Sheet 07_Supplier_List
A1: Supplier Name | B1: Currency
A2: Dicker Data | B2: NZD
A3: Entelar ICT New Zealand | B3: NZD
A4: Go Wireless NZ Ltd | B4: NZD
A5: Ingram Micro NZ | B5: NZD
A6: Netpoleon Limited | B6: NZD
A7: NextGen Distribution Ltd | B7: NZD
A8: Westcon NZ | B8: NZD
A9: Aatrox Communications Pty Ltd | B9: AUD
A10: Comvergence Pty Ltd | B10: AUD
A11: Dicker Data AU | B11: AUD
A12: Ingram Micro | B12: AUD
... A22: Vodafone Fiji Pte Ltd | B22: FJD

Sheet Approval Check
C4: Approval Check (margin + FX governance)
C6: Quote Number | D6: 0
C7: Client | D7: 0
C9: Subtotal (ex VAT) | D9: ='06_Quote_Output'!F64 -> 1058.4 | F9: Approval Thresholds
C10: Subtotal (in VAT) | D10: ='06_Quote_Output'!F65 -> 1190.7
C11: Estimated Landed Cost Total | D11: =SUMPRODUCT('02_Supplier_Input'!E:E, '02_Supplier_Input'!O:O) -> 793.8 | F11: Low Margin Threshold | G11: 0.08
C12: Gross Margin (FJD) | D12: =D9-D11 -> 264.6 | F12: Critical Margin Threshold | G12: 0.05
C13: Gross Margin % | D13: =IFERROR(D12 / D9, 0)*100 -> 25
C14: Number of Suppliers | D14: =IFERROR(__xludf.DUMMYFUNCTION("COUNTUNIQUE('02_Supplier_Input'!B2:B1005)"),4) -> 4
F18: Approval Status
C19: FX Freshness Check
C20: If FX rates are older than (hours) | D20: 240
C21: FX Status (manual review) | D21: CHECK
